bpx/__init__.py
bpx/expression_parser.py
bpx/function.py
bpx/interpolated_table.py
bpx/parsers.py
bpx/schema.py
bpx/utilities.py
bpx/validators.py
bpx-0.4.0.dist-info/WHEEL
bpx-0.4.0.dist-info/METADATA
bpx-0.4.0.dist-info/RECORD
