Metadata-Version: 2.1
Name: bpx
Version: 0.4.0
Summary: BPX schema and parsers
Author-email: Martin Robinson <martin.robinson@dtc.ox.ac.uk>
Requires-Dist: devtools
Requires-Dist: pydantic<2
Requires-Dist: pyparsing
Requires-Dist: coverage ; extra == "dev"
Requires-Dist: flake8>=3 ; extra == "dev"
Requires-Dist: sphinx>=6 ; extra == "dev"
Requires-Dist: sphinx_rtd_theme>=0.5 ; extra == "dev"
Requires-Dist: pydata-sphinx-theme ; extra == "dev"
Requires-Dist: sphinx_design ; extra == "dev"
Requires-Dist: sphinx-copybutton ; extra == "dev"
Requires-Dist: myst-parser ; extra == "dev"
Requires-Dist: sphinx-inline-tabs ; extra == "dev"
Provides-Extra: dev
